LICENSE
MANIFEST.in
README.md
setup.py
getdoi/__init__.py
getdoi.egg-info/PKG-INFO
getdoi.egg-info/SOURCES.txt
getdoi.egg-info/dependency_links.txt
getdoi.egg-info/requires.txt
getdoi.egg-info/top_level.txt
getdoi/getArticleURL/__init__.py
getdoi/getArticleURL/getArticleURLController.py
getdoi/getArticleURL/getArticleURLControllerStandAlone.py
getdoi/getArticleURL/gettableArticleURL.py
getdoi/getArticleURL/googleScholar.py
getdoi/getArticleURL/translateGoogleScholarQuery.py
getdoi/getDOIFromURL/__init__.py
getdoi/getDOIFromURL/brillonline.py
getdoi/getDOIFromURL/getDOIFromURLController.py
getdoi/getDOIFromURL/getDOIFromURLControllerStandAlone.py
getdoi/getDOIFromURL/gettableDOI.py
getdoi/getDOIFromURL/liebertpub.py
getdoi/getDOIFromURL/nature.py
getdoi/getDOIFromURL/plos.py
getdoi/getDOIFromURL/pmc.py
getdoi/getDOIFromURL/psycnet.py
getdoi/getDOIFromURL/sagepub.py
getdoi/getDOIFromURL/science.py
getdoi/getDOIFromURL/sciencedirect.py
getdoi/getDOIFromURL/springer.py
getdoi/getDOIFromURL/tandfonline.py
getdoi/getDOIFromURL/wiley.py
getdoi/reader/__init__.py
getdoi/reader/ioTextFile.py
getdoi/reader/readEnteredText.py
getdoi/scraping/__init__.py
getdoi/scraping/beautifulSoupModel.py
getdoi/standAlone/__init__.py
getdoi/tests/__init__.py
getdoi/tests/test_all.py
getdoi/tests/test_apa.py
getdoi/tests/test_beautifulSoupModel.py
getdoi/tests/test_brillonline.py
getdoi/tests/test_getArticleInfoFromCitationController.py
getdoi/tests/test_getDOIFromURLPresenter.py
getdoi/tests/test_liebertpub.py
getdoi/tests/test_main.py
getdoi/tests/test_nature.py
getdoi/tests/test_plos.py
getdoi/tests/test_pmc.py
getdoi/tests/test_psycnet.py
getdoi/tests/test_readEnteredText.py
getdoi/tests/test_readTextFile.py
getdoi/tests/test_sagepub.py
getdoi/tests/test_science.py
getdoi/tests/test_sciencedirect.py
getdoi/tests/test_springer.py
getdoi/tests/test_tandfonline.py
getdoi/tests/test_translateEscapeSequence.py
getdoi/tests/test_translatorKebabCase.py
getdoi/tests/test_translatorScholarQuery.py
getdoi/tests/test_wiley.py
getdoi/translator/__init__.py
getdoi/translator/translateEscapeSequence.py
getdoi/translator/translatorKebabCase.py
