Metadata-Version: 1.1
Name: getdoi
Version: 0.1.1
Summary: Get journal's DOI from article citation text.
Home-page: https://github.com/YutoMizutani/getdoi
Author: Yuto Mizutani
Author-email: yuto.mizutani.dev@gmail.com
License: MIT License
